winpwn/__init__.py
winpwn/context.py
winpwn/dbg.py
winpwn/misc.py
winpwn/var.py
winpwn/win.py
winpwn/winpwn.py
zepwn-0.0.4.dist-info/METADATA
zepwn-0.0.4.dist-info/WHEEL
zepwn-0.0.4.dist-info/top_level.txt
zepwn-0.0.4.dist-info/RECORD
